asym_crypto_yaml/__init__.py
asym_crypto_yaml/crypto.py
scripts/__init__.py
scripts/asym_crypto_yaml.py
asym_crypto_yaml-0.1.2.dist-info/LICENSE
asym_crypto_yaml-0.1.2.dist-info/METADATA
asym_crypto_yaml-0.1.2.dist-info/WHEEL
asym_crypto_yaml-0.1.2.dist-info/entry_points.txt
asym_crypto_yaml-0.1.2.dist-info/top_level.txt
asym_crypto_yaml-0.1.2.dist-info/RECORD
