Metadata-Version: 2.1
Name: asym-crypto-yaml
Version: 0.1.2
Summary: UNKNOWN
Home-page: UNKNOWN
License: UNKNOWN
Platform: UNKNOWN
Requires-Python: >=3.8
License-File: LICENSE
Requires-Dist: cryptography
Requires-Dist: click
Requires-Dist: pyyaml
